mt5connect/DB.py
mt5connect/Monitoring.py
mt5connect/__init__.py
mt5connect/archives/helpers/H_get_CME_contract.py
mt5connect/archives/helpers/H_mt5_data_fetch.py
mt5connect/archives/helpers/H_ticks_to_range.py
mt5connect/archives/helpers/__init__.py
mt5connect/archives/helpers/analyze_trade_duration.py
mt5connect/archives/helpers/calculate_average_freq.py
mt5connect/archives/helpers/calculate_pf_stats.py
mt5connect/archives/helpers/calculate_risk_free.py
mt5connect/archives/helpers/get_average_trade_duration.py
mt5connect/archives/helpers/get_data.py
mt5connect/archives/helpers/get_realized_pf_value.py
mt5connect/archives/helpers/plot_lines.py
mt5connect/archives/helpers/save_to_csv.py
mt5connect/archives/tests.py
mt5connect/logger_opensearch.py
mt5connect/mt5/Base.py
mt5connect/mt5/Sample_DWX.py
mt5connect/mt5/Trader.py
mt5connect/mt5/dwx_client.py
mt5connect/mt5/enums.py
mt5connect/mt5/equity/calculate_equity.py
mt5connect/mt5/equity/load_and_concat_data.py
mt5connect/mt5/equity/s3.py
mt5connect/tests/test_main.py
mt5connect/tg_send.py
mt5connect/wine_helpers/WineHelper.py
mt5connect/wine_helpers/w_account_info.py
mt5connect/wine_helpers/w_connect.py
mt5connect/wine_helpers/w_convert_tojson.py
mt5connect/wine_helpers/w_copy_rates.py
mt5connect/wine_helpers/w_initialize.py
mt5connect/wine_helpers/w_symbol.py
mt5connect/wine_helpers/w_timeframe.py
mt5connect-0.3.3.dist-info/METADATA
mt5connect-0.3.3.dist-info/WHEEL
mt5connect-0.3.3.dist-info/RECORD
