Metadata-Version: 2.1
Name: mt5connect
Version: 0.3.3
Summary: 
Author: Alpha
Author-email: piotr@piotryordanov.com
Requires-Python: >=3.11,<4.0
Classifier: Programming Language :: Python :: 3
Classifier: Programming Language :: Python :: 3.11
Requires-Dist: boto3 (>=1.28.37,<2.0.0)
Requires-Dist: build (>=1.0.3,<2.0.0)
Requires-Dist: numpy (>=1.24.4,<2.0.0)
Requires-Dist: opensearch-py (>=2.3.2,<3.0.0)
Requires-Dist: pandas (>=2.0.3,<3.0.0)
Requires-Dist: pika (>=1.3.2,<2.0.0)
Requires-Dist: psutil (>=5.9.6,<6.0.0)
Requires-Dist: pyarrow (>=13.0.0,<14.0.0)
Requires-Dist: pytest (>=7.4.0,<8.0.0)
Requires-Dist: pytest-watcher (>=0.3.4,<0.4.0)
Requires-Dist: pyzmq (>=25.1.1,<26.0.0)
Requires-Dist: requests (>=2.31.0,<3.0.0)
